{
  "cash": 27098.302833601832,
  "positions": {
    "DKNG": 5,
    "PYPL": 5,
    "SHOP": 1,
    "NOW": 1,
    "UBER": 2,
    "AMZN": 1,
    "ROKU": 1,
    "CRM": 1,
    "PANW": 1,
    "SOL-USD": 1,
    "XRP-USD": 109,
    "ADA-USD": 595,
    "DOGE-USD": 1021,
    "AVAX-USD": 14,
    "LINK-USD": 15,
    "LTC-USD": 3,
    "ATOM-USD": 81,
    "FIL-USD": 114,
    "ETC-USD": 19,
    "XLM-USD": 940
  },
  "entry_prices": {
    "DKNG": 24.940000534057617,
    "PYPL": 44.13999938964844,
    "SHOP": 122.30000305175781,
    "NOW": 114.0199966430664,
    "UBER": 76.55010223388672,
    "AMZN": 207.6699981689453,
    "ROKU": 95.11000061035156,
    "CRM": 196.3300018310547,
    "PANW": 169.9600067138672,
    "SOL-USD": 88.20909118652344,
    "XRP-USD": 1.4484918117523193,
    "ADA-USD": 0.26656511425971985,
    "DOGE-USD": 0.0931801050901413,
    "AVAX-USD": 9.448677062988281,
    "LINK-USD": 8.988999366760254,
    "LTC-USD": 55.139862060546875,
    "ATOM-USD": 1.8409626483917236,
    "FIL-USD": 0.8933141827583313,
    "ETC-USD": 8.325725555419922,
    "XLM-USD": 0.1662643551826477
  }
}